README.rst
setup.py
transparent_keras/__init__.py
transparent_keras/transparent_model.py
transparent_keras.egg-info/PKG-INFO
transparent_keras.egg-info/SOURCES.txt
transparent_keras.egg-info/dependency_links.txt
transparent_keras.egg-info/requires.txt
transparent_keras.egg-info/top_level.txt
transparent_keras/tests/__init__.py
transparent_keras/tests/test_transparent_model.py