Metadata-Version: 1.1
Name: transparent-keras
Version: 0.3.1
Summary: Provide a drop-in replacement for a Keras Model that allows a look under the hood during training
Home-page: UNKNOWN
Author: Angelos Katharopoulos <katharas@gmail.com>
Author-email: katharas@gmail.com
License: MIT
Platform: UNKNOWN
Classifier: Intended Audience :: Science/Research
Classifier: Intended Audience :: Developers
Classifier: License :: OSI Approved :: MIT License
Classifier: Topic :: Scientific/Engineering
Classifier: Programming Language :: Python
Classifier: Programming Language :: Python :: 2
Classifier: Programming Language :: Python :: 2.7
Classifier: Programming Language :: Python :: 3
Classifier: Programming Language :: Python :: 3.4
Classifier: Programming Language :: Python :: 3.5
